qm_saas/__init__.py
qm_saas/api.py
qm_saas/client.py
qm_saas-1.1.7.dist-info/METADATA
qm_saas-1.1.7.dist-info/WHEEL
qm_saas-1.1.7.dist-info/licenses/LICENSE
qm_saas-1.1.7.dist-info/RECORD
