Metadata-Version: 2.4
Name: qm-saas
Version: 1.1.7
Summary: QM Simulator as a Service is a client library to launch simulator instances for QUA programs.
License: BSD-3-Clause
License-File: LICENSE
Author: Quantum Machines
Author-email: info@quantum-machines.co
Requires-Python: >=3.9,<3.14
Classifier: License :: OSI Approved :: BSD License
Classifier: Programming Language :: Python :: 3
Classifier: Programming Language :: Python :: 3.9
Classifier: Programming Language :: Python :: 3.10
Classifier: Programming Language :: Python :: 3.11
Classifier: Programming Language :: Python :: 3.12
Classifier: Programming Language :: Python :: 3.13
Requires-Dist: deprecation (>=2.0.0)
Requires-Dist: h11 (>=0.16.0)
Requires-Dist: h2 (>=4.3.0)
Requires-Dist: protobuf (>=4.25.8)
Requires-Dist: requests (>=2.32.5)
Requires-Dist: urllib3 (>=1.26)
